{
  "alias": "alexandreagarza",
  "username": "Alex Garza",
  "descriptionProfile": [
    "Youtube Content Creator & Vlogger 👻:AlexandreaGarza 🎥Youtube.com/TheAlexandreaGarza ⬇️ Spring Favorites vid! ⬇️",
    "Youtube Content Creator & Vlogger 👻:AlexandreaGarza 🎥Youtube.com/TheAlexandreaGarza ⬇️ Spring Favorites vid! ⬇️"
  ],
  "urlProfile": "https://www.instagram.com/alexandreagarza/",
  "urlImgProfile": "https://scontent.cdninstagram.com/t51.2885-19/s320x320/17125525_398154657216436_8331665302114795520_a.jpg",
  "website": "youtu.be/c1VZt31fIAQ",
  "numberPosts": 756,
  "numberFollowers": 217445,
  "numberFollowing": 411,
  "private": false,
  "posts": [
    {
      "url": "https://www.instagram.com/p/BTh0UYMFUJd/?taken-by=alexandreagarza",
      "urlImage": "https://scontent.cdninstagram.com/t51.2885-15/s640x640/sh0.08/e35/18161897_237603326716101_7435419083295686656_n.jpg",
      "isVideo": false,
      "multipleImage": false,
      "tags": [
        "#dior"
      ],
      "mentions": [
        "@dior",
        "@dior"
      ],
      "description": "New video is live on my channel, direct link in bio if you want to see what's in the bag! I picked up a couple new @dior pieces for Spring! I'm also sharing all of my current favorite beauty products, clothes and shoes that I've been loving recently! April faves mixed with a little Haul 💕 Hope you love it! #dior",
      "localization": null,
      "date": "2017-04-30T05:00:00.000Z",
      "numberLikes": 2894,
      "filename": "18161897_237603326716101_7435419083295686656_n.jpg"
    },
    {
      "url": "https://www.instagram.com/p/BTeixDXFayS/?taken-by=alexandreagarza",
      "urlImage": "https://scontent.cdninstagram.com/t51.2885-15/s640x640/sh0.08/e35/18161959_210406049463076_2857310603792351232_n.jpg",
      "isVideo": false,
      "multipleImage": false,
      "tags": [
        "#liketkit",
        "#springootd",
        "#springstyle"
      ],
      "mentions": [
        "@liketoknow",
        "@michael_maddalena",
        "@marc.fisher",
        "@liketoknow.it"
      ],
      "description": "Happy Saturday ✨ My favorite espadrilles on sale right now and there are still a couple sizes left! So comfy and cute 💕 I have 3 pairs of these jeans too bc they're the best and under $60! All outfit details here: http://liketk.it/2rc8c #liketkit @liketoknow.it #springootd #springstyle",
      "localization": null,
      "date": "2017-04-29T05:00:00.000Z",
      "numberLikes": 7673,
      "filename": "18161959_210406049463076_2857310603792351232_n.jpg"
    },
    {
      "url": "https://www.instagram.com/p/BTZPPiNFlD4/?taken-by=alexandreagarza",
      "urlImage": "https://scontent.cdninstagram.com/t51.2885-15/s640x640/sh0.08/e35/c0.133.1080.1080/18095238_1285192474921088_3100958824274591744_n.jpg",
      "isVideo": false,
      "multipleImage": false,
      "tags": [
        "#liketkit"
      ],
      "mentions": [
        "@liketoknow",
        "@gucci",
        "@rebeccaminkoff",
        "@shopbop",
        "@michael_maddalena",
        "@liketoknow.it"
      ],
      "description": "So happy you guys loved Tuesdays video! Direct link in bio if you haven't seen it yet. Here's another look at my outfit from the show! This dress would be perfect for a bridal or baby shower, graduation or any spring occasion! Outfit details here: http://liketk.it/2raLz #liketkit @liketoknow.it",
      "localization": null,
      "date": "2017-04-27T05:00:00.000Z",
      "numberLikes": 9848,
      "filename": "18095238_1285192474921088_3100958824274591744_n.jpg"
    },
    {
      "url": "https://www.instagram.com/p/BTVB1nhlRoR/?taken-by=alexandreagarza",
      "urlImage": "https://scontent.cdninstagram.com/t51.2885-15/s640x640/sh0.08/e35/18096119_1672254613082268_1437620876475367424_n.jpg",
      "isVideo": false,
      "multipleImage": false,
      "tags": [],
      "mentions": [
        "@misshayleypaige"
      ],
      "description": "Can you spot me?! 🙋🏼 New video is live, direct link in bio! I was so lucky to attend bridal fashion week so I wanted to bring you guys with me. I filmed a GRWM so you could see exactly how I do my hair and makeup for an event. I'm also sharing my spring outfit, perfect for any special occasion like a shower or party! Then come to 2 shows with me and sit front row and see all of the new gowns 💕💕 I had a blast filming this video I know you guys will love it! It reminds me of my wedding series I filmed when I was engaged. If you're getting married soon or just love fashion this is a MUST WATCH! 😘",
      "localization": "Chelsea Market",
      "date": "2017-04-25T05:00:00.000Z",
      "numberLikes": 2842,
      "filename": "18096119_1672254613082268_1437620876475367424_n.jpg"
    },
    {
      "url": "https://www.instagram.com/p/BTSI1JMlnAW/?taken-by=alexandreagarza",
      "urlImage": "https://scontent.cdninstagram.com/t51.2885-15/s640x640/sh0.08/e35/18161090_1311437692310625_3438276102479413248_n.jpg",
      "isVideo": false,
      "multipleImage": false,
      "tags": [
        "#springstyle",
        "#ootd"
      ],
      "mentions": [
        "@clubmonaco",
        "@clubmonaco",
        "@freepeople"
      ],
      "description": "Adding lots of blush pink, nudes and whites to my closet this Spring! Everything at @clubmonaco right now is gorg 💕 Do you guys want me to film a Spring Clothing Essentials video? #springstyle #ootd",
      "localization": "Club Monaco Somerset Collection",
      "date": "2017-04-24T05:00:00.000Z",
      "numberLikes": 9244,
      "filename": "18161090_1311437692310625_3438276102479413248_n.jpg"
    },
    {
      "url": "https://www.instagram.com/p/BTPfy_mFD_v/?taken-by=alexandreagarza",
      "urlImage": "https://scontent.cdninstagram.com/t51.2885-15/s640x640/sh0.08/e35/18094816_612587622277462_4095723406656274432_n.jpg",
      "isVideo": false,
      "multipleImage": false,
      "tags": [
        "#spring"
      ],
      "mentions": [
        "@frontgate",
        "@target",
        "@target",
        "@frontgate"
      ],
      "description": "New blooms for the front porch 🌺 Check out my insta stories and Snapchat to see more ☀️ Rug is from @frontgate and gardening tools are from @target #spring",
      "localization": null,
      "date": "2017-04-23T05:00:00.000Z",
      "numberLikes": 4627,
      "filename": "18094816_612587622277462_4095723406656274432_n.jpg"
    },
    {
      "url": "https://www.instagram.com/p/BTOzly5FE76/?taken-by=alexandreagarza",
      "urlImage": "https://scontent.cdninstagram.com/t51.2885-15/e35/c236.0.607.607/18095733_1288312111222400_4433460148547092480_n.jpg",
      "isVideo": false,
      "multipleImage": false,
      "tags": [
        "#liketkit"
      ],
      "mentions": [
        "@liketoknow",
        "@gucci",
        "@aliceandolivia",
        "@shopbop",
        "@nordstrom",
        "@revolve",
        "@marc.fisher",
        "@liketoknow.it",
        "@tularosalabel",
        "@grlfrnd_denim",
        "@goodamerican",
        "@liketoknow.it.home"
      ],
      "description": "New video is live, direct link in bio! I found the BEST JEANS EVER and I'm sharing them with you! Also, how to style each denim trend for Spring so there are 5 outfit ideas! Here's a peek at my 3 favorite jeans. I'm telling you these jeans are amazing- slimming, lifting, lengthening! 👍🏼👍🏼👍🏼 To shop these 3 outfits now: http://liketk.it/2r7Jr #liketkit @liketoknow.it",
      "localization": null,
      "date": "2017-04-23T05:00:00.000Z",
      "numberLikes": 7242,
      "filename": "18095733_1288312111222400_4433460148547092480_n.jpg"
    },
    {
      "url": "https://www.instagram.com/p/BTMt__ZFUoH/?taken-by=alexandreagarza",
      "urlImage": "https://scontent.cdninstagram.com/t51.2885-15/s640x640/sh0.08/e35/18094924_963897260413991_2884210095636348928_n.jpg",
      "isVideo": false,
      "multipleImage": false,
      "tags": [
        "#nybfw",
        "#hayleypaige"
      ],
      "mentions": [
        "@misshayleypaige",
        "@lazarobridal",
        "@misshayleypaige",
        "@lazarobridal"
      ],
      "description": "Last night was incredible at the @misshayleypaige and @lazarobridal shows! 💎 I still can't get over Hayley's new designs, she's such a game changer for bridal! I filmed the whole thing so you guys can experience it too, it'll be up soon. In the meantime check my insta stories before is disappears! ✨ #nybfw #hayleypaige",
      "localization": "Chelsea Market",
      "date": "2017-04-22T05:00:00.000Z",
      "numberLikes": 3114,
      "filename": "18094924_963897260413991_2884210095636348928_n.jpg"
    },
    {
      "url": "https://www.instagram.com/p/BTJ_XKKlcuK/?taken-by=alexandreagarza",
      "urlImage": "https://scontent.cdninstagram.com/t51.2885-15/s640x640/sh0.08/e35/c0.134.1080.1080/18014047_325322127883045_3695182070960619520_n.jpg",
      "isVideo": false,
      "multipleImage": false,
      "tags": [
        "#liketkit"
      ],
      "mentions": [
        "@liketoknow",
        "@gucci",
        "@dior",
        "@diormakeup"
      ],
      "description": "Shopping in Soho 🖤 Enjoying our last day in NYC! My top and jacket are Zara, I linked everything else. This bag is perfect for walking around because it's lightweight and durable 👍🏼 Outfit details here: http://liketk.it/2r6Hw #liketkit @liketoknow.it",
      "localization": "Christian Dior Soho",
      "date": "2017-04-21T05:00:00.000Z",
      "numberLikes": 10381,
      "filename": "18014047_325322127883045_3695182070960619520_n.jpg"
    },
    {
      "url": "https://www.instagram.com/p/BTIFLWZFwM5/?taken-by=alexandreagarza",
      "urlImage": "https://scontent.cdninstagram.com/t51.2885-15/s640x640/sh0.08/e35/18012144_1794386507544612_901317776331767808_n.jpg",
      "isVideo": false,
      "multipleImage": false,
      "tags": [
        "#ad"
      ],
      "mentions": [
        "@ole_henriksen",
        "@sephora"
      ],
      "description": "My new favorite Vitamin C serum from @ole_henriksen! As you guys know I love anything that hydrates and fights dullness/aging. I've been using Truth Serum every morning to keep my skin bright and glowy! It's great for getting that glow without makeup. It's oil-free and smells like oranges, yum! You can find the serum at @sephora #ad",
      "localization": null,
      "date": "2017-04-20T05:00:00.000Z",
      "numberLikes": 5091,
      "filename": "18012144_1794386507544612_901317776331767808_n.jpg"
    },
    {
      "url": "https://www.instagram.com/p/BTH5zZEl_Uu/?taken-by=alexandreagarza",
      "urlImage": "https://scontent.cdninstagram.com/t51.2885-15/s640x640/sh0.08/e35/18013157_107070293188001_5893772260665196544_n.jpg",
      "isVideo": false,
      "multipleImage": false,
      "tags": [],
      "mentions": [],
      "description": "Roses on roses on roses 😍 They smelled amazing!",
      "localization": "Chelsea, Manhattan",
      "date": "2017-04-20T05:00:00.000Z",
      "numberLikes": 9911,
      "filename": "18013157_107070293188001_5893772260665196544_n.jpg"
    },
    {
      "url": "https://www.instagram.com/p/BTHjVNPF6DM/?taken-by=alexandreagarza",
      "urlImage": "https://scontent.cdninstagram.com/t51.2885-15/s640x640/sh0.08/e35/c0.135.1080.1080/18013714_1642062865808619_3506844327647117312_n.jpg",
      "isVideo": false,
      "multipleImage": false,
      "tags": [
        "#MyTrueBeauty",
        "#ad"
      ],
      "mentions": [
        "@ecotools",
        "@ecotools"
      ],
      "description": "Best day ever kicking off the #MyTrueBeauty tour with @ecotools ✨ We met so many beautiful, talented, hard working and sweet women today! You guys are the best 😘 I can't thank you guys enough for all of the support and love and taking time out of your busy day to meet me made my day! #ad",
      "localization": "New York University",
      "date": "2017-04-20T05:00:00.000Z",
      "numberLikes": 9937,
      "filename": "18013714_1642062865808619_3506844327647117312_n.jpg"
    },
    {
      "url": "https://www.instagram.com/p/BTHHtFRlQfG/?taken-by=alexandreagarza",
      "urlImage": "https://scontent.cdninstagram.com/t51.2885-15/s640x640/sh0.08/e35/c0.55.1080.1080/18012052_528198180901928_2460571014233325568_n.jpg",
      "isVideo": false,
      "multipleImage": false,
      "tags": [
        "#NYC"
      ],
      "mentions": [],
      "description": "On my way to find a good latte at Chelsea Market before my meetup this afternoon! Last nights panel was awesome, we vlogged the whole thing 💕  #NYC",
      "localization": "Chelsea Market",
      "date": "2017-04-20T05:00:00.000Z",
      "numberLikes": 6065,
      "filename": "18012052_528198180901928_2460571014233325568_n.jpg"
    },
    {
      "url": "https://www.instagram.com/p/BTCsIpXlUH3/?taken-by=alexandreagarza",
      "urlImage": "https://scontent.cdninstagram.com/t51.2885-15/s640x640/sh0.08/e35/18013282_306738099757458_2527207977291612160_n.jpg",
      "isVideo": false,
      "multipleImage": false,
      "tags": [
        "#mytruebeauty",
        "#ad"
      ],
      "mentions": [
        "@ecotools",
        "@ecotools"
      ],
      "description": "Packing my brushes and headed to NYC! ✨ The @ecotools mobile tour is launching this week and I'm having a meet up to celebrate! If you're in the NYC area I would LOVE to meet you! We will be meeting this Thursday April 20th from 12-2 pm on the NYU Campus: 20-26 Astor Pl. (corner closest to the Walgreens) 💕Can't wait! #mytruebeauty #ad",
      "localization": null,
      "date": "2017-04-18T05:00:00.000Z",
      "numberLikes": 4317,
      "filename": "18013282_306738099757458_2527207977291612160_n.jpg"
    },
    {
      "url": "https://www.instagram.com/p/BTCJnolFYk6/?taken-by=alexandreagarza",
      "urlImage": "https://scontent.cdninstagram.com/t51.2885-15/s640x640/sh0.08/e35/18011546_1957414584544818_3332982591216156672_n.jpg",
      "isVideo": false,
      "multipleImage": false,
      "tags": [
        "#liketkit",
        "#springstyle",
        "#springootd"
      ],
      "mentions": [
        "@liketoknow",
        "@topshop",
        "@aliceandolivia",
        "@louboutinworld",
        "@michael_maddalena",
        "@louisvuitton",
        "@liketoknow.it"
      ],
      "description": "Spring vibes ✨ Running around like crazy today before we leave for NYC in the morning! Can't wait to meet some of you at the meetup on Thursday! Outfit details: http://liketk.it/2r4rI #liketkit @liketoknow.it #springstyle #springootd",
      "localization": null,
      "date": "2017-04-18T05:00:00.000Z",
      "numberLikes": 12810,
      "filename": "18011546_1957414584544818_3332982591216156672_n.jpg"
    },
    {
      "url": "https://www.instagram.com/p/BS_50lxlD-1/?taken-by=alexandreagarza",
      "urlImage": "https://scontent.cdninstagram.com/t51.2885-15/s640x640/sh0.08/e35/18011193_802230039932943_1700685793699299328_n.jpg",
      "isVideo": false,
      "multipleImage": false,
      "tags": [],
      "mentions": [
        "@mirandafryejewelry",
        "@studio30nails"
      ],
      "description": "Doodle nails ✨💎 The white is opi funny bunny!",
      "localization": null,
      "date": "2017-04-17T05:00:00.000Z",
      "numberLikes": 6422,
      "filename": "18011193_802230039932943_1700685793699299328_n.jpg"
    },
    {
      "url": "https://www.instagram.com/p/BS9Qf15lZle/?taken-by=alexandreagarza",
      "urlImage": "https://scontent.cdninstagram.com/t51.2885-15/s640x640/sh0.08/e35/c0.72.1080.1080/18011235_1900024976932938_3575009800846573568_n.jpg",
      "isVideo": false,
      "multipleImage": false,
      "tags": [
        "#liketkit",
        "#easter",
        "#ootd",
        "#springstyle"
      ],
      "mentions": [
        "@liketoknow",
        "@aliceandolivia",
        "@louboutinworld",
        "@victoriabeckham",
        "@louisvuitton",
        "@target",
        "@liketoknow.it"
      ],
      "description": "Hope you're all having an amazing Easter! 💕 I'm obsessed with this dress it's $35 and comes in black too! Size down if you want more of a fitted look. Shop my entire outfit here: http://liketk.it/2r39B #liketkit @liketoknow.it #easter #ootd #springstyle",
      "localization": null,
      "date": "2017-04-16T05:00:00.000Z",
      "numberLikes": 13438,
      "filename": "18011235_1900024976932938_3575009800846573568_n.jpg"
    }
  ]
}