{
  "alias": "alice_gao",
  "username": "ALICE GAO",
  "descriptionProfile": [
    "NYC-based Portfolio: alicegao.com Tinker Street *",
    "NYC-based Portfolio: alicegao.com Tinker Street *"
  ],
  "urlProfile": "https://www.instagram.com/alice_gao/",
  "urlImgProfile": "https://scontent.cdninstagram.com/t51.2885-19/s320x320/12353377_1677127242544992_1981815541_a.jpg",
  "website": "lingered-upon.com",
  "numberPosts": 3452,
  "numberFollowers": 990123,
  "numberFollowing": 396,
  "private": false,
  "posts": [
    {
      "url": "https://www.instagram.com/p/BThsG-bl5r4/?taken-by=alice_gao",
      "urlImage": "https://scontent.cdninstagram.com/t51.2885-15/s640x640/sh0.08/e35/c0.135.1080.1080/18252040_101553333743332_1208301929612967936_n.jpg",
      "isVideo": false,
      "multipleImage": false,
      "tags": [
        "#SapphireOnLocation",
        "#vegasuncorkd",
        "#sponsored"
      ],
      "mentions": [
        "@Chase",
        "@chase"
      ],
      "description": "ended my vegas uncork'd experience with the most beautiful lunch at julian serrano's picasso restaurant (see all the dishes on stories). thank you @Chase Sapphire for the good times! all of you Sapphire card holders who had food envy should check it out for next year 😉. #SapphireOnLocation #vegasuncorkd #sponsored",
      "localization": "Picasso (restaurant)",
      "date": "2017-04-30T05:00:00.000Z",
      "numberLikes": 2774,
      "filename": "18252040_101553333743332_1208301929612967936_n.jpg"
    },
    {
      "url": "https://www.instagram.com/p/BTg3voLlpJj/?taken-by=alice_gao",
      "urlImage": "https://scontent.cdninstagram.com/t51.2885-15/s640x640/sh0.08/e35/c0.135.1080.1080/18162184_1906444922943685_2133453329873764352_n.jpg",
      "isVideo": false,
      "multipleImage": false,
      "tags": [],
      "mentions": [],
      "description": "look up",
      "localization": "Delano Las Vegas at Mandalay Bay",
      "date": "2017-04-30T05:00:00.000Z",
      "numberLikes": 4693,
      "filename": "18162184_1906444922943685_2133453329873764352_n.jpg"
    },
    {
      "url": "https://www.instagram.com/p/BTftrWZlGp7/?taken-by=alice_gao",
      "urlImage": "https://scontent.cdninstagram.com/t51.2885-15/s640x640/sh0.08/e35/c0.135.1080.1080/18160577_197216827463552_9151772870446153728_n.jpg",
      "isVideo": false,
      "multipleImage": false,
      "tags": [
        "#SapphireOnLocation",
        "#vegasuncorkd",
        "#sponsored"
      ],
      "mentions": [
        "@Chase",
        "@chase"
      ],
      "description": "epic brunch at Alain Ducasse's Rivea today with @Chase Sapphire Reserve. this linguini and clams was one of many highlights. check out the view from this 64th floor restaurant on stories!\n// #SapphireOnLocation #vegasuncorkd #sponsored",
      "localization": "Delano Las Vegas at Mandalay Bay",
      "date": "2017-04-29T05:00:00.000Z",
      "numberLikes": 4334,
      "filename": "18160577_197216827463552_9151772870446153728_n.jpg"
    },
    {
      "url": "https://www.instagram.com/p/BTewylnlfoU/?taken-by=alice_gao",
      "urlImage": "https://scontent.cdninstagram.com/t51.2885-15/s640x640/sh0.08/e35/c0.135.1080.1080/18096557_367961270265882_3197967854724972544_n.jpg",
      "isVideo": false,
      "multipleImage": false,
      "tags": [],
      "mentions": [],
      "description": "plate still life",
      "localization": "Caesars Palace",
      "date": "2017-04-29T05:00:00.000Z",
      "numberLikes": 3944,
      "filename": "18096557_367961270265882_3197967854724972544_n.jpg"
    },
    {
      "url": "https://www.instagram.com/p/BTeirdXFjtV/?taken-by=alice_gao",
      "urlImage": "https://scontent.cdninstagram.com/t51.2885-15/s640x640/sh0.08/e35/c0.135.1080.1080/18160895_1973115269589624_2818036508009693184_n.jpg",
      "isVideo": false,
      "multipleImage": false,
      "tags": [
        "#SapphireOnLocation",
        "#sponsored"
      ],
      "mentions": [
        "@Chase",
        "@bonappetitmag"
      ],
      "description": "hello from vegas! if you've seen my stories you'll know i've partnered with @Chase Sapphire to experience @bonappetitmag's Vegas Uncork'd. last night was the grand tasting at Caesars Palace, which was basically the biggest \"buffet\" i've ever been to. so fun to experience over 50 chefs' signature dishes (should have worn stretchy pants)! #SapphireOnLocation #sponsored",
      "localization": "Caesars Palace",
      "date": "2017-04-29T05:00:00.000Z",
      "numberLikes": 4709,
      "filename": "18160895_1973115269589624_2818036508009693184_n.jpg"
    },
    {
      "url": "https://www.instagram.com/p/BTZTZ1eluT0/?taken-by=alice_gao",
      "urlImage": "https://scontent.cdninstagram.com/t51.2885-15/s640x640/sh0.08/e35/c180.0.719.719/18013153_726095860932359_479332549395480576_n.jpg",
      "isVideo": false,
      "multipleImage": false,
      "tags": [],
      "mentions": [
        "@jessifrederick",
        "@tibi"
      ],
      "description": "wispy",
      "localization": "Joshua Tree National Park",
      "date": "2017-04-27T05:00:00.000Z",
      "numberLikes": 4263,
      "filename": "18013153_726095860932359_479332549395480576_n.jpg"
    },
    {
      "url": "https://www.instagram.com/p/BTY1XA3lNhG/?taken-by=alice_gao",
      "urlImage": "https://scontent.cdninstagram.com/t51.2885-15/s640x640/sh0.08/e35/c0.135.1080.1080/18013663_1882600182017923_2607363714986278912_n.jpg",
      "isVideo": false,
      "multipleImage": false,
      "tags": [],
      "mentions": [
        "@psartmuseum",
        "@psartmuseum"
      ],
      "description": "detail of judith godwin's \"epic\"\n(great abstract expressionism exhibit ft all women artists at @psartmuseum right now!)",
      "localization": "Palm Springs Art Museum",
      "date": "2017-04-27T05:00:00.000Z",
      "numberLikes": 4927,
      "filename": "18013663_1882600182017923_2607363714986278912_n.jpg"
    },
    {
      "url": "https://www.instagram.com/p/BTW2meRhCth/?taken-by=alice_gao",
      "urlImage": "https://scontent.cdninstagram.com/t51.2885-15/s640x640/sh0.08/e35/c0.135.1080.1080/18013438_756722721172140_11856811271389184_n.jpg",
      "isVideo": false,
      "multipleImage": false,
      "tags": [],
      "mentions": [
        "@jessifrederick",
        "@loandsons"
      ],
      "description": "behind the scenes, shootin' in the craziest wind",
      "localization": null,
      "date": "2017-04-26T05:00:00.000Z",
      "numberLikes": 6571,
      "filename": "18013438_756722721172140_11856811271389184_n.jpg"
    },
    {
      "url": "https://www.instagram.com/p/BTWina2FLSn/?taken-by=alice_gao",
      "urlImage": "https://scontent.cdninstagram.com/t51.2885-15/s640x640/sh0.08/e35/c0.135.1080.1080/18160776_1866705250258233_4796692838509182976_n.jpg",
      "isVideo": false,
      "multipleImage": false,
      "tags": [],
      "mentions": [],
      "description": "hair brush cactus",
      "localization": null,
      "date": "2017-04-26T05:00:00.000Z",
      "numberLikes": 3220,
      "filename": "18160776_1866705250258233_4796692838509182976_n.jpg"
    },
    {
      "url": "https://www.instagram.com/p/BTVkdS8FnE1/?taken-by=alice_gao",
      "urlImage": "https://scontent.cdninstagram.com/t51.2885-15/s640x640/sh0.08/e35/c0.135.1080.1080/18160695_927341030741106_8322770850046541824_n.jpg",
      "isVideo": false,
      "multipleImage": false,
      "tags": [],
      "mentions": [
        "@twobunchpalms",
        "@twobunchpalms"
      ],
      "description": "best seat in the house\n@twobunchpalms",
      "localization": "Two Bunch Palms",
      "date": "2017-04-26T05:00:00.000Z",
      "numberLikes": 4542,
      "filename": "18160695_927341030741106_8322770850046541824_n.jpg"
    },
    {
      "url": "https://www.instagram.com/p/BTUyzE9lU2q/?taken-by=alice_gao",
      "urlImage": "https://scontent.cdninstagram.com/t51.2885-15/s640x640/sh0.08/e35/c0.135.1080.1080/18161446_286554595123868_8039797062893568000_n.jpg",
      "isVideo": false,
      "multipleImage": false,
      "tags": [],
      "mentions": [],
      "description": "type love",
      "localization": "Palm Springs Art Museum",
      "date": "2017-04-25T05:00:00.000Z",
      "numberLikes": 4739,
      "filename": "18161446_286554595123868_8039797062893568000_n.jpg"
    },
    {
      "url": "https://www.instagram.com/p/BTUT7_ploMk/?taken-by=alice_gao",
      "urlImage": "https://scontent.cdninstagram.com/t51.2885-15/s640x640/sh0.08/e35/c0.135.1080.1080/18013653_735043093344127_1743365506489909248_n.jpg",
      "isVideo": false,
      "multipleImage": false,
      "tags": [],
      "mentions": [
        "@protagonistnyc"
      ],
      "description": "away",
      "localization": "Joshua Tree National Park",
      "date": "2017-04-25T05:00:00.000Z",
      "numberLikes": 7909,
      "filename": "18013653_735043093344127_1743365506489909248_n.jpg"
    },
    {
      "url": "https://www.instagram.com/p/BTUHhbqlay9/?taken-by=alice_gao",
      "urlImage": "https://scontent.cdninstagram.com/t51.2885-15/s640x640/sh0.08/e35/c0.135.1080.1080/18095047_216272848866397_577500087144415232_n.jpg",
      "isVideo": false,
      "multipleImage": false,
      "tags": [],
      "mentions": [],
      "description": "hideaway",
      "localization": "Elvis Honeymoon Hideaway",
      "date": "2017-04-25T05:00:00.000Z",
      "numberLikes": 5188,
      "filename": "18095047_216272848866397_577500087144415232_n.jpg"
    },
    {
      "url": "https://www.instagram.com/p/BTS3sX0FWkA/?taken-by=alice_gao",
      "urlImage": "https://scontent.cdninstagram.com/t51.2885-15/s640x640/sh0.08/e35/c0.135.1080.1080/18094648_119298568623556_5639765901914931200_n.jpg",
      "isVideo": false,
      "multipleImage": false,
      "tags": [],
      "mentions": [
        "@twobunchpalms",
        "@jessifrederick",
        "@twobunchpalms"
      ],
      "description": "wandering the grounds @twobunchpalms",
      "localization": "Two Bunch Palms",
      "date": "2017-04-24T05:00:00.000Z",
      "numberLikes": 4856,
      "filename": "18094648_119298568623556_5639765901914931200_n.jpg"
    },
    {
      "url": "https://www.instagram.com/p/BTR5HstlTYB/?taken-by=alice_gao",
      "urlImage": "https://scontent.cdninstagram.com/t51.2885-15/s640x640/sh0.08/e35/c108.0.863.863/17881916_1515264031825258_8688796887953702912_n.jpg",
      "isVideo": false,
      "multipleImage": false,
      "tags": [],
      "mentions": [],
      "description": "dawn in the desert\n(and discovered my finger makes a decent built in filter on the iphone camera 😂)",
      "localization": null,
      "date": "2017-04-24T05:00:00.000Z",
      "numberLikes": 3767,
      "filename": "17881916_1515264031825258_8688796887953702912_n.jpg"
    },
    {
      "url": "https://www.instagram.com/p/BTRXH3xlGq_/?taken-by=alice_gao",
      "urlImage": "https://scontent.cdninstagram.com/t51.2885-15/s640x640/sh0.08/e35/c0.135.1080.1080/18013839_1703521723273830_5031345756796092416_n.jpg",
      "isVideo": false,
      "multipleImage": false,
      "tags": [],
      "mentions": [
        "@jessifrederick"
      ],
      "description": "channeling ralph gibson\n(and damn it is windy out here!!)",
      "localization": null,
      "date": "2017-04-24T05:00:00.000Z",
      "numberLikes": 5200,
      "filename": "18013839_1703521723273830_5031345756796092416_n.jpg"
    },
    {
      "url": "https://www.instagram.com/p/BTPzcqJl62N/?taken-by=alice_gao",
      "urlImage": "https://scontent.cdninstagram.com/t51.2885-15/s640x640/sh0.08/e35/c0.135.1080.1080/18013670_1448937861846737_6253021926805995520_n.jpg",
      "isVideo": false,
      "multipleImage": false,
      "tags": [],
      "mentions": [],
      "description": "i 💚the desert",
      "localization": "Sunnylands",
      "date": "2017-04-23T05:00:00.000Z",
      "numberLikes": 5718,
      "filename": "18013670_1448937861846737_6253021926805995520_n.jpg"
    }
  ]
}