{
  "alias": "marycake",
  "username": null,
  "descriptionProfile": [
    "snap/tweet @himarycake • tk♡ ✎ inquiries: kiana@vampped.com",
    "snap/tweet",
    "• tk♡ ✎ inquiries: kiana@vampped.com"
  ],
  "urlProfile": "https://www.instagram.com/marycake/",
  "urlImgProfile": "https://scontent.cdninstagram.com/t51.2885-19/s320x320/15538599_182127992258812_1170289123991224320_a.jpg",
  "website": null,
  "numberPosts": 1004,
  "numberFollowers": 602000,
  "numberFollowing": 245,
  "private": false,
  "posts": [
    {
      "url": "https://www.instagram.com/p/BTU0fG-FY3L/?taken-by=marycake",
      "urlImage": "https://scontent.cdninstagram.com/t51.2885-15/s640x640/sh0.08/e35/c1.0.1078.1078/18013544_2043094875944753_7654032424740847616_n.jpg",
      "numberLikes": 4542,
      "numberViews": 0,
      "numberComments": 7,
      "isVideo": false,
      "multipleImage": false,
      "tags": [
        "#ad"
      ],
      "mentions": [
        "@sugarbearhair",
        "@sugarbearhair"
      ],
      "description": "sugar, ah honey honey ♪ you are my candy girl @sugarbearhair #ad",
      "localization": null,
      "date": "2017-04-25T05:00:00.000Z",
      "filename": "18013544_2043094875944753_7654032424740847616_n.jpg"
    },
    {
      "url": "https://www.instagram.com/p/BTPzh6slS_e/?taken-by=marycake",
      "urlImage": "https://scontent.cdninstagram.com/t51.2885-15/s640x640/sh0.08/e35/c0.95.1080.1080/18094673_1667228523306925_8720342447785246720_n.jpg",
      "numberLikes": 119000,
      "numberViews": 0,
      "numberComments": 40,
      "isVideo": false,
      "multipleImage": false,
      "tags": [],
      "mentions": [
        "@museumoficecream",
        "@lackofcoloraus",
        "@ootdfash",
        "@museumoficecream",
        "@glvssbrvnd"
      ],
      "description": "melting for you @museumoficecream",
      "localization": "MUSEUM OF ICE CREAM",
      "date": "2017-04-23T05:00:00.000Z",
      "filename": "18094673_1667228523306925_8720342447785246720_n.jpg"
    },
    {
      "url": "https://www.instagram.com/p/BTM1ZKsl5tl/?taken-by=marycake",
      "urlImage": "https://scontent.cdninstagram.com/t51.2885-15/s640x640/sh0.08/e35/c0.135.1080.1080/17881059_1330338600347874_4293804012697812992_n.jpg",
      "numberLikes": 112000,
      "numberViews": 0,
      "numberComments": 45,
      "isVideo": false,
      "multipleImage": false,
      "tags": [],
      "mentions": [
        "@ootdfash",
        "@ootdfash"
      ],
      "description": "took a stroll through the museum of ice dreams last night- typo intended. wearing @ootdfash dress + necklace- use \"marycake\" for 15% off 🌷",
      "localization": "MUSEUM OF ICE CREAM",
      "date": "2017-04-22T05:00:00.000Z",
      "filename": "17881059_1330338600347874_4293804012697812992_n.jpg"
    },
    {
      "url": "https://www.instagram.com/p/BTLCilClACU/?taken-by=marycake",
      "urlImage": "https://scontent.cdninstagram.com/t51.2885-15/s640x640/sh0.08/e35/c0.135.1080.1080/17882372_606838439522302_4114096894496473088_n.jpg",
      "numberLikes": 9306,
      "numberViews": 0,
      "numberComments": 34,
      "isVideo": false,
      "multipleImage": false,
      "tags": [],
      "mentions": [
        "@celinelinarte",
        "@kkarmalove"
      ],
      "description": "sugar, spice, & everything nice",
      "localization": "MUSEUM OF ICE CREAM",
      "date": "2017-04-21T05:00:00.000Z",
      "filename": "17882372_606838439522302_4114096894496473088_n.jpg"
    },
    {
      "url": "https://www.instagram.com/p/BTC4_OblNOn/?taken-by=marycake",
      "urlImage": "https://scontent.cdninstagram.com/t51.2885-15/s640x640/sh0.08/e35/c0.120.1080.1080/17883116_1346035388825667_6095535706673774592_n.jpg",
      "numberLikes": 195000,
      "numberViews": 0,
      "numberComments": 43,
      "isVideo": false,
      "multipleImage": false,
      "tags": [
        "#revolvefestival"
      ],
      "mentions": [
        "@revolve",
        "@revolve",
        "@ootdfash",
        "@glvssbrvnd"
      ],
      "description": "pink vibes in this tularosa dress for the last day 🌸 @revolve #revolvefestival",
      "localization": null,
      "date": "2017-04-18T05:00:00.000Z",
      "filename": "17883116_1346035388825667_6095535706673774592_n.jpg"
    },
    {
      "url": "https://www.instagram.com/p/BTAhUyYFNYT/?taken-by=marycake",
      "urlImage": "https://scontent.cdninstagram.com/t51.2885-15/s640x640/sh0.08/e35/c0.22.1080.1080/17934560_197394294101318_1150674970423066624_n.jpg",
      "numberLikes": 155000,
      "numberViews": 0,
      "numberComments": 18,
      "isVideo": false,
      "multipleImage": false,
      "tags": [
        "#revolvefestival"
      ],
      "mentions": [
        "@aftersicecream",
        "@ootdfash",
        "@glvssbrvnd",
        "@revolve",
        "@aftersicecream"
      ],
      "description": "lookin back at the weekend like. 🎡 @aftersicecream milk+cereal | @ootdfash hat + bag | @glvssbrvnd aviators | @revolve tularosa dress #revolvefestival",
      "localization": null,
      "date": "2017-04-17T05:00:00.000Z",
      "filename": "17934560_197394294101318_1150674970423066624_n.jpg"
    },
    {
      "url": "https://www.instagram.com/p/BS8I8OyFmKG/?taken-by=marycake",
      "urlImage": "https://scontent.cdninstagram.com/t51.2885-15/s640x640/sh0.08/e35/c0.134.1080.1080/17931881_1907306606218953_3118617736930918400_n.jpg",
      "numberLikes": 129000,
      "numberViews": 0,
      "numberComments": 14,
      "isVideo": false,
      "multipleImage": false,
      "tags": [
        "#revolvefestival"
      ],
      "mentions": [
        "@ootdfash",
        "@glvssbrvnd",
        "@revolve"
      ],
      "description": "im on the right track baby | @ootdfash hat + necklace | @glvssbrvnd aviators | @revolve tularosa set #revolvefestival",
      "localization": null,
      "date": "2017-04-16T05:00:00.000Z",
      "filename": "17931881_1907306606218953_3118617736930918400_n.jpg"
    },
    {
      "url": "https://www.instagram.com/p/BS7dGVJlYmf/?taken-by=marycake",
      "urlImage": "https://scontent.cdninstagram.com/t51.2885-15/s640x640/sh0.08/e35/c0.87.1080.1080/17931909_1130109593783877_1735301709686636544_n.jpg",
      "numberLikes": 143000,
      "numberViews": 0,
      "numberComments": 12,
      "isVideo": false,
      "multipleImage": false,
      "tags": [
        "#blackfilenails",
        "#blackfile"
      ],
      "mentions": [
        "@aftersicecream",
        "@blackfilenails",
        "@aftersicecream",
        "@blackfilenails"
      ],
      "description": "two door cinema club + @aftersicecream 🍦 rose gold gel nails by @blackfilenails #blackfilenails #blackfile",
      "localization": null,
      "date": "2017-04-15T05:00:00.000Z",
      "filename": "17931909_1130109593783877_1735301709686636544_n.jpg"
    },
    {
      "url": "https://www.instagram.com/p/BS7DhoAFIcd/?taken-by=marycake",
      "urlImage": "https://scontent.cdninstagram.com/t51.2885-15/s640x640/sh0.08/e35/c0.60.1080.1080/17931803_441405719542743_5070323989461598208_n.jpg",
      "numberLikes": 129000,
      "numberViews": 0,
      "numberComments": 28,
      "isVideo": false,
      "multipleImage": false,
      "tags": [
        "#revolvefestival"
      ],
      "mentions": [
        "@ootdfash",
        "@glvssbrvnd",
        "@revolve",
        "@revolve",
        "@ootdfash",
        "@glvssbrvnd"
      ],
      "description": "edc day two lmao 🌹hat: @ootdfash | glasses: @glvssbrvnd sunnies | privacy please bodysuit: @revolve | #revolvefestival",
      "localization": null,
      "date": "2017-04-15T05:00:00.000Z",
      "filename": "17931803_441405719542743_5070323989461598208_n.jpg"
    },
    {
      "url": "https://www.instagram.com/p/BS41iFeFlbZ/?taken-by=marycake",
      "urlImage": "https://scontent.cdninstagram.com/t51.2885-15/s640x640/sh0.08/e35/c0.91.1080.1080/17818802_208189253012513_791090279653310464_n.jpg",
      "numberLikes": 198000,
      "numberViews": 0,
      "numberComments": 30,
      "isVideo": false,
      "multipleImage": false,
      "tags": [
        "#revolvefestival"
      ],
      "mentions": [
        "@aftersicecream",
        "@revolve",
        "@revolve",
        "@aftersicecream"
      ],
      "description": "festival essential: @aftersicecream // @revolve lovers+friends 2 piece #revolvefestival",
      "localization": null,
      "date": "2017-04-14T05:00:00.000Z",
      "filename": "17818802_208189253012513_791090279653310464_n.jpg"
    }
  ]
}