{
  "alias": "pierlu__igi",
  "username": "Pier Luigi",
  "descriptionProfile": [
    "🇮🇹 Marche | Italy 📬 hello.pierluigi@gmail.com >> @simpleframes",
    "🇮🇹 Marche | Italy 📬 hello.pierluigi@gmail.com >>"
  ],
  "urlProfile": "https://www.instagram.com/pierlu__igi/",
  "urlImgProfile": "https://scontent.cdninstagram.com/t51.2885-19/s320x320/17126380_1647197811973583_5293547823680192512_a.jpg",
  "website": "500px.com/pierlu__igi",
  "numberPosts": 1481,
  "numberFollowers": 71000,
  "numberFollowing": 333,
  "private": false,
  "posts": [
    {
      "url": "https://www.instagram.com/p/BTUf3k0lzLt/?taken-by=pierlu__igi",
      "urlImage": "https://scontent.cdninstagram.com/t51.2885-15/s640x640/sh0.08/e35/c0.135.1080.1080/18096617_410230512687060_6898384460027265024_n.jpg",
      "numberLikes": 1745,
      "numberViews": 0,
      "numberComments": 36,
      "isVideo": false,
      "multipleImage": false,
      "tags": [
        "#LoveOrvieto",
        "#OrvietoSocialTour",
        "#spring4igers",
        "#cntraveler",
        "#guiderepubblica",
        "#italy",
        "#italia",
        "#italia365",
        "#whatitalyis",
        "#bellaitalia",
        "#instaitalia",
        "#vscoitaly",
        "#vscophile",
        "#huffpostgram",
        "#huntgram",
        "#guardiantravelsnaps",
        "#passionpassport",
        "#openmyworld",
        "#tlpicks",
        "#athomeintheworld",
        "#exklusive_shot",
        "#freedomthinkers",
        "#canon",
        "#teamcanon",
        "#comeandsee",
        "#places_wow",
        "#instatravel",
        "#discoverglobe",
        "#agameoftones"
      ],
      "mentions": [
        "@love_orvieto"
      ],
      "description": "Una delle cose che mi sono piaciute di più ad Orvieto è questa unione bellissima tra tradizione e innovazione. Uno degli esempi più significativi è l'azienda agracola Janas, dove due giovani, provenienti da Sicilia e Sardegna, da alcuni anni coltivano con successo grani antichi. #LoveOrvieto #OrvietoSocialTour\n.\n.\n.\n.\n.\n.\n.\n.\n.\n.\n#spring4igers #cntraveler #guiderepubblica #italy #italia #italia365 #whatitalyis #bellaitalia #instaitalia #vscoitaly #vscophile #huffpostgram #huntgram #guardiantravelsnaps #passionpassport #openmyworld #tlpicks #athomeintheworld #exklusive_shot #freedomthinkers #canon #teamcanon #comeandsee #places_wow #instatravel #discoverglobe #agameoftones",
      "localization": "La Locanda di Colle Ombroso - Azienda Agricola JANAS",
      "date": "2017-04-25T05:00:00.000Z",
      "filename": "18096617_410230512687060_6898384460027265024_n.jpg"
    },
    {
      "url": "https://www.instagram.com/p/BTTmIQ9lGDm/?taken-by=pierlu__igi",
      "urlImage": "https://scontent.cdninstagram.com/t51.2885-15/s640x640/sh0.08/e35/c0.134.1080.1080/18013287_1288088081310580_5841021927602257920_n.jpg",
      "numberLikes": 2278,
      "numberViews": 0,
      "numberComments": 80,
      "isVideo": false,
      "multipleImage": false,
      "tags": [
        "#LoveOrvieto",
        "#OrvietoSocialTour",
        "#exploremore",
        "#optoutside",
        "#italy",
        "#italia",
        "#italia365",
        "#whatitalyis",
        "#bellaitalia",
        "#instaitalia",
        "#vscoitaly",
        "#vscophile",
        "#huffpostgram",
        "#huntgram",
        "#guardiantravelsnaps",
        "#passionpassport",
        "#openmyworld",
        "#tlpicks",
        "#athomeintheworld",
        "#cntraveler",
        "#freedomthinkers",
        "#canon",
        "#teamcanon",
        "#comeandsee",
        "#places_wow",
        "#instatravel",
        "#tasteintravel",
        "#agameoftones",
        "#guiderepubblica"
      ],
      "mentions": [
        "@love_orvieto"
      ],
      "description": "Con la testa ancora immersa nel verde della campagna umbra... #LoveOrvieto #OrvietoSocialTour\n.\n.\n.\n.\n.\n.\n.\n#exploremore #optoutside #italy #italia #italia365 #whatitalyis #bellaitalia #instaitalia #vscoitaly #vscophile #huffpostgram #huntgram #guardiantravelsnaps #passionpassport #openmyworld #tlpicks #athomeintheworld #cntraveler #freedomthinkers #canon #teamcanon #comeandsee #places_wow #instatravel #tasteintravel #agameoftones #guiderepubblica",
      "localization": "Orvieto",
      "date": "2017-04-25T05:00:00.000Z",
      "filename": "18013287_1288088081310580_5841021927602257920_n.jpg"
    },
    {
      "url": "https://www.instagram.com/p/BTRHD51lVfD/?taken-by=pierlu__igi",
      "urlImage": "https://scontent.cdninstagram.com/t51.2885-15/s640x640/sh0.08/e35/c0.134.1080.1080/18095251_1891151657824939_3994617054714920960_n.jpg",
      "numberLikes": 2456,
      "numberViews": 0,
      "numberComments": 130,
      "isVideo": false,
      "multipleImage": false,
      "tags": [
        "#LoveOrvieto",
        "#OrvietoSocialTour",
        "#guiderepubblica",
        "#cntraveler",
        "#exploremore",
        "#optoutside",
        "#italy",
        "#italia",
        "#italia365",
        "#whatitalyis",
        "#bellaitalia",
        "#instaitalia",
        "#vscoitaly",
        "#vscophile",
        "#huffpostgram",
        "#huntgram",
        "#guardiantravelsnaps",
        "#passionpassport",
        "#openmyworld",
        "#tlpicks",
        "#athomeintheworld",
        "#exklusive_shot",
        "#freedomthinkers",
        "#canon",
        "#teamcanon",
        "#comeandsee",
        "#places_wow",
        "#instatravel",
        "#discoverglobe",
        "#agameoftones"
      ],
      "mentions": [
        "@love_orvieto"
      ],
      "description": "Orvieto, così come l'Umbria, è un tesoro tutto da scoprire, a volte basta aprire una finestra. #LoveOrvieto #OrvietoSocialTour\n.\n.\n.\n.\n.\n.\n#guiderepubblica #cntraveler #exploremore #optoutside #italy #italia #italia365 #whatitalyis #bellaitalia #instaitalia #vscoitaly #vscophile #huffpostgram #huntgram #guardiantravelsnaps #passionpassport #openmyworld #tlpicks #athomeintheworld #exklusive_shot #freedomthinkers #canon #teamcanon #comeandsee #places_wow #instatravel #discoverglobe #agameoftones",
      "localization": "Orvieto",
      "date": "2017-04-24T05:00:00.000Z",
      "filename": "18095251_1891151657824939_3994617054714920960_n.jpg"
    },
    {
      "url": "https://www.instagram.com/p/BTOfD9IFeOu/?taken-by=pierlu__igi",
      "urlImage": "https://scontent.cdninstagram.com/t51.2885-15/s640x640/sh0.08/e35/c0.134.1080.1080/18094987_171277523395045_6578963876753178624_n.jpg",
      "numberLikes": 2104,
      "numberViews": 0,
      "numberComments": 76,
      "isVideo": false,
      "multipleImage": false,
      "tags": [
        "#LoveOrvieto",
        "#OrvietoSocialTour"
      ],
      "mentions": [
        "@love_orvieto",
        "@love_orvieto"
      ],
      "description": "A volte una foto non basta a raccontare un posto, le sue persone e le sue ricchezze. In questi tre giorni siamo rimasti colpiti dalla vitalità di questa piccola cittadina umbra, che sa coniugare molto bene tradizione e modernità. \nUn grazie di cuore agli amici di @love_orvieto e a tutte le persone che ci hanno accompagnati in questo tour, coccolandoci e facendoci sentire come a casa. Spero davvero di tornare presto in questa parte d'Italia a cui sono particolarmente legato. \n#LoveOrvieto #OrvietoSocialTour",
      "localization": "Duomo di Orvieto",
      "date": "2017-04-23T05:00:00.000Z",
      "filename": "18094987_171277523395045_6578963876753178624_n.jpg"
    },
    {
      "url": "https://www.instagram.com/p/BTMA9ArFbii/?taken-by=pierlu__igi",
      "urlImage": "https://scontent.cdninstagram.com/t51.2885-15/s640x640/sh0.08/e35/c0.134.1080.1080/18011601_1861296664138001_6462863935715409920_n.jpg",
      "numberLikes": 2693,
      "numberViews": 0,
      "numberComments": 88,
      "isVideo": false,
      "multipleImage": false,
      "tags": [
        "#LoveOrvieto",
        "#OrvietoSocialTour"
      ],
      "mentions": [
        "@alexcoda_",
        "@love_orvieto"
      ],
      "description": "Luci, colori, dettagli che adoro e che solo in questa parte d'Italia si possono trovare, assieme ad uno stile di vita lento e genuino. #LoveOrvieto #OrvietoSocialTour",
      "localization": "Orvieto",
      "date": "2017-04-22T05:00:00.000Z",
      "filename": "18011601_1861296664138001_6462863935715409920_n.jpg"
    },
    {
      "url": "https://www.instagram.com/p/BTKLE5nFRPt/?taken-by=pierlu__igi",
      "urlImage": "https://scontent.cdninstagram.com/t51.2885-15/s640x640/sh0.08/e35/c0.134.1080.1080/18011270_1846074232313247_6131671783385858048_n.jpg",
      "numberLikes": 2321,
      "numberViews": 0,
      "numberComments": 128,
      "isVideo": false,
      "multipleImage": false,
      "tags": [
        "#LoveOrvieto",
        "#OrvietoSocialTour",
        "#cntraveler",
        "#exploremore",
        "#optoutside",
        "#italy",
        "#italia",
        "#italia365",
        "#whatitalyis",
        "#bellaitalia",
        "#instaitalia",
        "#vscoitaly",
        "#vscophile",
        "#huffpostgram",
        "#huntgram",
        "#guardiantravelsnaps",
        "#passionpassport",
        "#openmyworld",
        "#tlpicks",
        "#athomeintheworld",
        "#exklusive_shot",
        "#freedomthinkers",
        "#canon",
        "#teamcanon",
        "#comeandsee",
        "#places_wow",
        "#instatravel",
        "#discoverglobe",
        "#agameoftones"
      ],
      "mentions": [
        "@love_orvieto"
      ],
      "description": "È sempre bello tornare in Umbria, una regione che ha tanto in comune con le Marche, eppure si mostra assai diversa. Da oggi a domenica avrò il piacere di esplorare Orvieto e le sue ricchezze artistiche ed eno-gastronomiche assime ad un bel gruppo di igers. Seguiteci su #LoveOrvieto e #OrvietoSocialTour\n.\n.\n.\n.\n.\n#cntraveler #exploremore #optoutside #italy #italia #italia365 #whatitalyis #bellaitalia #instaitalia #vscoitaly #vscophile #huffpostgram #huntgram #guardiantravelsnaps #passionpassport #openmyworld #tlpicks #athomeintheworld #exklusive_shot #freedomthinkers #canon #teamcanon #comeandsee #places_wow #instatravel #discoverglobe #agameoftones",
      "localization": "Orvieto",
      "date": "2017-04-21T05:00:00.000Z",
      "filename": "18011270_1846074232313247_6131671783385858048_n.jpg"
    },
    {
      "url": "https://www.instagram.com/p/BTE6XLiFTlG/?taken-by=pierlu__igi",
      "urlImage": "https://scontent.cdninstagram.com/t51.2885-15/s640x640/sh0.08/e35/c0.134.1080.1080/18011992_414277712277786_1170604885691858944_n.jpg",
      "numberLikes": 2735,
      "numberViews": 0,
      "numberComments": 129,
      "isVideo": false,
      "multipleImage": false,
      "tags": [
        "#spring4igers"
      ],
      "mentions": [],
      "description": "Colpo d'occhio marchigiano. #spring4igers",
      "localization": "Marche",
      "date": "2017-04-19T05:00:00.000Z",
      "filename": "18011992_414277712277786_1170604885691858944_n.jpg"
    },
    {
      "url": "https://www.instagram.com/p/BTCXZr6l93Z/?taken-by=pierlu__igi",
      "urlImage": "https://scontent.cdninstagram.com/t51.2885-15/s640x640/sh0.08/e35/c0.134.1080.1080/17932632_610469399157767_6781735708068413440_n.jpg",
      "numberLikes": 3300,
      "numberViews": 0,
      "numberComments": 181,
      "isVideo": false,
      "multipleImage": false,
      "tags": [
        "#spring4igers"
      ],
      "mentions": [],
      "description": "The favorite season is coming. #spring4igers",
      "localization": "Numana",
      "date": "2017-04-18T05:00:00.000Z",
      "filename": "17932632_610469399157767_6781735708068413440_n.jpg"
    },
    {
      "url": "https://www.instagram.com/p/BS_3sfZlzz6/?taken-by=pierlu__igi",
      "urlImage": "https://scontent.cdninstagram.com/t51.2885-15/s640x640/sh0.08/e35/c0.134.1080.1080/18011525_161013351091425_1605737136370221056_n.jpg",
      "numberLikes": 2708,
      "numberViews": 0,
      "numberComments": 140,
      "isVideo": false,
      "multipleImage": false,
      "tags": [],
      "mentions": [
        "@flavio_romagnoli"
      ],
      "description": "Se lo vuoi, per goderti certi spettacoli della natura puoi anche farti 8km in mezzo ai boschi e tornare a casa felice.",
      "localization": "Pian Grande, Monte Conero",
      "date": "2017-04-17T05:00:00.000Z",
      "filename": "18011525_161013351091425_1605737136370221056_n.jpg"
    },
    {
      "url": "https://www.instagram.com/p/BS1dF4OlUOW/?taken-by=pierlu__igi",
      "urlImage": "https://scontent.cdninstagram.com/t51.2885-15/s640x640/sh0.08/e35/c0.134.1080.1080/17882399_632181986973914_5983325558602203136_n.jpg",
      "numberLikes": 3556,
      "numberViews": 0,
      "numberComments": 223,
      "isVideo": false,
      "multipleImage": false,
      "tags": [
        "#lamialiguria",
        "#liveauthentic",
        "#ig_italia",
        "#tasteintravel",
        "#socality",
        "#rsa_streetview",
        "#italian_places",
        "#way2ill",
        "#streetdreamsmag",
        "#urbanromantix",
        "#lifeofadventure",
        "#igersitalia",
        "#igmasters"
      ],
      "mentions": [
        "@turismoinliguria"
      ],
      "description": "Cleaning up the archives before new adventures.\n.\n.\n.\n.\n.\n.\n.\n#lamialiguria #liveauthentic #ig_italia #tasteintravel #socality #rsa_streetview #italian_places #way2ill #streetdreamsmag #urbanromantix #lifeofadventure #igersitalia #igmasters",
      "localization": "Manarola",
      "date": "2017-04-13T05:00:00.000Z",
      "filename": "17882399_632181986973914_5983325558602203136_n.jpg"
    }
  ]
}