{
  "alias": "runnerspace",
  "username": "RunnerSpace.com",
  "descriptionProfile": [
    "The latest in track & field/XC from RunnerSpace.com #runnerspace Twitter: RunnerSpace_com",
    "The latest in track & field/XC from RunnerSpace.com",
    "Twitter: RunnerSpace_com"
  ],
  "urlProfile": "https://www.instagram.com/runnerspace/",
  "urlImgProfile": "https://scontent.cdninstagram.com/t51.2885-19/s320x320/15623926_1857808444506089_7937522711775936512_a.jpg",
  "website": "runnerspace.com",
  "numberPosts": 4625,
  "numberFollowers": 361000,
  "numberFollowing": 733,
  "private": false,
  "posts": [
    {
      "url": "https://www.instagram.com/p/BTVDl0plheW/?taken-by=runnerspace",
      "urlImage": "https://scontent.cdninstagram.com/t51.2885-15/s640x640/sh0.08/e35/18161207_126134824599226_444408563993935872_n.jpg",
      "numberLikes": 10008,
      "numberViews": 0,
      "numberComments": 11,
      "isVideo": false,
      "multipleImage": false,
      "tags": [
        "#gbm2017",
        "#usarc",
        "#tracknation",
        "#RunnerSpace",
        "#Instarunners",
        "#usatf",
        "#DyeStat"
      ],
      "mentions": [
        "@mackeykb",
        "@claytonmurphy",
        "@usatf",
        "@claytonmurphy",
        "@mackeykb"
      ],
      "description": "@mackeykb and @claytonmurphy, 2017 @usatf 1 Mile Road Champions! Katie ran 4:37.00 and Clayton ran 3:59.96! On demand race replays will be on www.usatf.tv soon! #gbm2017 #usarc #tracknation #RunnerSpace #Instarunners #usatf #DyeStat",
      "localization": "Des Moines, Iowa",
      "date": "2017-04-25T05:00:00.000Z",
      "filename": "18161207_126134824599226_444408563993935872_n.jpg"
    },
    {
      "url": "https://www.instagram.com/p/BTUwQv7lbur/?taken-by=runnerspace",
      "urlImage": "https://scontent.cdninstagram.com/t51.2885-15/s640x640/sh0.08/e35/18012029_447652945588322_937392679824654336_n.jpg",
      "numberLikes": 8393,
      "numberViews": 0,
      "numberComments": 183,
      "isVideo": false,
      "multipleImage": false,
      "tags": [
        "#RunnerSpace",
        "#drakerelays",
        "#mondolove",
        "#usatf",
        "#usatftv",
        "#usatf",
        "#DyeStat",
        "#Instarunners",
        "#tracknation"
      ],
      "mentions": [],
      "description": "The Drake Relays women’s 1500m is going to be epic. If you think you have what it takes to guess the winner you could win a a year of RunnerSpace +PLUS!! Comment below wi the winner’s name & time to win! - Entry Example: Shelby Houlihan 4:03.32 - Entries (Subject to change, check runnerspace.com for the latest entries)\nNikki Hamblin\nMarta Freitas\nShelby Houlihan\nAlexa Efraimson\nAmanda Eccleston\nNicole Siguientes\nCharlene Lipsey\nKate Grace\nKaela Edwards\nSara Vaughn\nSammy Watson\n- Watch the Drake Relays live on USATF.TV this Thursday through Saturday!\n- Contest Rules: Entries are due by Friday, April 28 at Noon ET. Only 1 entry per account. If you submit more than 1 entry the 1st one will be used. Whoever picks the correct athlete & time will be declared the winner. In the event of a tie because no entry matches the correct athlete & time, whoever picked the correct athlete and is closest to the winning time without being slower than the actual time is declared the winner. If we still have a tie whoever posted the correct entry first will be declared the winner. The winner will be announced in the comment section of this post by Sunday, April 30.\n- #RunnerSpace #drakerelays #mondolove #usatf #usatftv #usatf #DyeStat #Instarunners #tracknation",
      "localization": null,
      "date": "2017-04-25T05:00:00.000Z",
      "filename": "18012029_447652945588322_937392679824654336_n.jpg"
    },
    {
      "url": "https://www.instagram.com/p/BTUKG5LlUTz/?taken-by=runnerspace",
      "urlImage": "https://scontent.cdninstagram.com/t51.2885-15/s640x640/sh0.08/e35/18160372_1486066528118424_6939766766276968448_n.jpg",
      "numberLikes": 5622,
      "numberViews": 0,
      "numberComments": 13,
      "isVideo": false,
      "multipleImage": false,
      "tags": [
        "#runnerspace",
        "#tracknation",
        "#trackandfield",
        "#trailrunning",
        "#training",
        "#track",
        "#awesome",
        "#xc",
        "#crosscountry",
        "#teammates",
        "#regram",
        "#running",
        "#fitness",
        "#outdoortrack",
        "#friends",
        "#training",
        "#team"
      ],
      "mentions": [
        "@lisannedewitte",
        "@aalimartinezz",
        "@juliabrunette_",
        "@croixprovence",
        "@natat4t",
        "@ana",
        "@laurengrazis",
        "@kaizergillispie",
        "@zvlv"
      ],
      "description": "Do you have any plans for an awesome group run or race this week?\n-\nHere’s our latest batch of group shots you guys have tagged with #runnerspace!\n-\nPhotos by @lisannedewitte @aalimartinezz @juliabrunette_ @croixprovence @natat4t @ana.braaten @laurengrazis @kaizergillispie @zvlv.x\n-\n#tracknation #trackandfield #trailrunning #training #track #awesome #xc #crosscountry #teammates #regram #running #fitness #outdoortrack #friends #training #team",
      "localization": null,
      "date": "2017-04-25T05:00:00.000Z",
      "filename": "18160372_1486066528118424_6939766766276968448_n.jpg"
    },
    {
      "url": "https://www.instagram.com/p/BTSCLxNFx3E/?taken-by=runnerspace",
      "urlImage": "https://scontent.cdninstagram.com/t51.2885-15/s640x640/sh0.08/e35/c180.0.720.720/18013907_1436913663035356_3807641498934050816_n.jpg",
      "numberLikes": 4233,
      "numberViews": 0,
      "numberComments": 15,
      "isVideo": false,
      "multipleImage": false,
      "tags": [
        "#Repost",
        "#dyestat",
        "#POW",
        "#tracknation",
        "#RunnerSpace",
        "#trackandfield"
      ],
      "mentions": [
        "@dyestat",
        "@dyestat",
        "@dyestat"
      ],
      "description": "Ok folks, go get to dyestat.com to vote for the @dyestat Performance of the Week!\n.\n#Repost @dyestat\n・・・\nIt’s time vote for the @dyestat Performance of the Week!\n\nVote for the POW at www.DyeStat.com! (Link in bio!) Valarie Allman\nJordan Hasay\nMary Keitany\nJasmine Moore\nJalen Reagor\nJelena Rowe\nGalen Rupp\nOdean Skeen\nTeam USA\nDaniel Wanjiru\n\n#dyestat #POW #tracknation #RunnerSpace #trackandfield",
      "localization": null,
      "date": "2017-04-24T05:00:00.000Z",
      "filename": "18013907_1436913663035356_3807641498934050816_n.jpg"
    },
    {
      "url": "https://www.instagram.com/p/BTPkvunFlgK/?taken-by=runnerspace",
      "urlImage": "https://scontent.cdninstagram.com/t51.2885-15/s640x640/sh0.08/e35/18096180_1869853539904329_1347347282458050560_n.jpg",
      "numberLikes": 6042,
      "numberViews": 0,
      "numberComments": 9,
      "isVideo": false,
      "multipleImage": false,
      "tags": [
        "#runnerspace",
        "#tracknation",
        "#instarunners",
        "#runchat",
        "#running",
        "#runners",
        "#xc",
        "#run",
        "#favorites",
        "#photooftheday",
        "#regram",
        "#repost",
        "#follow",
        "#shoutout",
        "#like",
        "#bestof",
        "#highlights",
        "#athletics",
        "#running"
      ],
      "mentions": [
        "@haasruns",
        "@drewhunter00",
        "@abigailmagnum",
        "@airlavillenie",
        "@jamiephelan",
        "@sherwood_xc",
        "@kylemerber",
        "@amymichellefoto",
        "@nickwillis"
      ],
      "description": "Here’s some of our favorite photos from you guys on Instagram from throughout the week. Keep posting awesome photos!\n-\nFeatured photos by @haasruns @drewhunter00 @abigailmagnum @airlavillenie @jamiephelan @sherwood_xc @kylemerber @amymichellefoto @nickwillis -\nGot a cool pic or video? Make sure you tag it with #runnerspace. We share the best of the best every weekend. -\n#tracknation #instarunners #runchat #running #runners #xc #run #favorites #photooftheday #regram #repost #follow #shoutout #like #bestof #highlights #athletics #running",
      "localization": null,
      "date": "2017-04-23T05:00:00.000Z",
      "filename": "18096180_1869853539904329_1347347282458050560_n.jpg"
    },
    {
      "url": "https://www.instagram.com/p/BTKYJ6El6W7/?taken-by=runnerspace",
      "urlImage": "https://scontent.cdninstagram.com/t51.2885-15/s640x640/sh0.08/e35/c142.0.796.796/18095289_1511834045495967_2587939669555544064_n.jpg",
      "numberLikes": 7936,
      "numberViews": 0,
      "numberComments": 48,
      "isVideo": false,
      "multipleImage": false,
      "tags": [
        "#Repost",
        "#regram",
        "#runnerspace",
        "#prom"
      ],
      "mentions": [
        "@vchrz12"
      ],
      "description": "👏👏\n.\n.\n#Repost @vchrz12\n・・・\nI got a surprise, roses, a baton, a poster, and a sweeeet prom date 😃💙 Also, good song choice Andrew😉 #regram #runnerspace #prom",
      "localization": null,
      "date": "2017-04-21T05:00:00.000Z",
      "filename": "18095289_1511834045495967_2587939669555544064_n.jpg"
    },
    {
      "url": "https://www.instagram.com/p/BTH-uOHlJB1/?taken-by=runnerspace",
      "urlImage": "https://scontent.cdninstagram.com/t51.2885-15/s640x640/sh0.08/e35/c180.0.720.720/18013536_1457537750943861_4373370425044893696_n.jpg",
      "numberLikes": 5405,
      "numberViews": 0,
      "numberComments": 96,
      "isVideo": false,
      "multipleImage": false,
      "tags": [
        "#centennial",
        "#Oregon",
        "#runnerspace",
        "#tracknation",
        "#instarunners"
      ],
      "mentions": [],
      "description": "The Centennial Invitational is live on RunnerSpace.com Saturday!\n.\nComment below with \"I want +PLUS!\" For a chance to win access to a year of RunnerSpace +PLUS!\n.\nWatch the meet live on RunnerSpace with a +PLUS account on Saturday!\n.\n#centennial #Oregon #runnerspace #tracknation #instarunners",
      "localization": "Centennial High School",
      "date": "2017-04-20T05:00:00.000Z",
      "filename": "18013536_1457537750943861_4373370425044893696_n.jpg"
    },
    {
      "url": "https://www.instagram.com/p/BTEvpIxl0SY/?taken-by=runnerspace",
      "urlImage": "https://scontent.cdninstagram.com/t51.2885-15/s640x640/sh0.08/e35/c14.0.1051.1051/17934235_1479833952092098_2856505645316702208_n.jpg",
      "numberLikes": 9986,
      "numberViews": 0,
      "numberComments": 47,
      "isVideo": false,
      "multipleImage": false,
      "tags": [
        "#Repost",
        "#regram",
        "#runnerspace",
        "#workoutwednesday"
      ],
      "mentions": [
        "@rudisha800m"
      ],
      "description": "When you and your training partners are on point.\n.\n.\n.\n#Repost @rudisha800m\n・・・\nReal workout as started.... #regram #runnerspace #workoutwednesday",
      "localization": null,
      "date": "2017-04-19T05:00:00.000Z",
      "filename": "17934235_1479833952092098_2856505645316702208_n.jpg"
    },
    {
      "url": "https://www.instagram.com/p/BTAFetKlsXh/?taken-by=runnerspace",
      "urlImage": "https://scontent.cdninstagram.com/t51.2885-15/s640x640/sh0.08/e35/c180.0.719.719/17932517_1933879643512548_3590062742096052224_n.jpg",
      "numberLikes": 6293,
      "numberViews": 0,
      "numberComments": 23,
      "isVideo": false,
      "multipleImage": false,
      "tags": [
        "#dyestat",
        "#dyestat",
        "#POW",
        "#tracknation",
        "#RunnerSpace",
        "#trackandfield"
      ],
      "mentions": [
        "@dyestat",
        "@dyestat",
        "@dyestat"
      ],
      "description": "Go vote!\n#dyestat @dyestat\n・・・\nIt’s time vote for the @dyestat Performance of the Week! Vote on DyeStat.com! (Link in @dyestat bio)\nShae Anderson\nJosh Kerr\nShelby Moran\nClayton Murphy\nOregon Women\nRaevyn Rogers\nDafne Schippers\nCooper Teare\nBen True\nVernon Turner\n\n#dyestat #POW #tracknation #RunnerSpace #trackandfield",
      "localization": null,
      "date": "2017-04-17T05:00:00.000Z",
      "filename": "17932517_1933879643512548_3590062742096052224_n.jpg"
    },
    {
      "url": "https://www.instagram.com/p/BS_l-OEFUcm/?taken-by=runnerspace",
      "urlImage": "https://scontent.cdninstagram.com/t51.2885-15/s640x640/sh0.08/e35/18011421_298845770553003_7688101776074997760_n.jpg",
      "numberLikes": 143000,
      "numberViews": 0,
      "numberComments": 43,
      "isVideo": false,
      "multipleImage": false,
      "tags": [
        "#Repost",
        "#usatf",
        "#marathon",
        "#running",
        "#teamusatf",
        "#teamusa",
        "#track",
        "#tracknation",
        "#trackandfield",
        "#regram",
        "#runnerspace"
      ],
      "mentions": [
        "@jordanhasay",
        "@usatf",
        "@jordanhasay",
        "@bostonmarathon",
        "@jhboston26"
      ],
      "description": "👏👏👏 @jordanhasay .\n.\n#Repost @usatf\n・・・\n@jordanhasay runs fastest 🇺🇸 marathon debut ever in 2:23:00 to finish 3️⃣rd at @bostonmarathon! That's the 4️⃣th-fastest marathon in #usatf history!\n•\n#marathon #running #teamusatf #teamusa #track #tracknation #trackandfield 📷@jhboston26/Twitter #regram #runnerspace",
      "localization": null,
      "date": "2017-04-17T05:00:00.000Z",
      "filename": "18011421_298845770553003_7688101776074997760_n.jpg"
    }
  ]
}